pactown/__init__.py
pactown/cli.py
pactown/config.py
pactown/error_context.py
pactown/events.py
pactown/fast_start.py
pactown/generator.py
pactown/iac.py
pactown/llm.py
pactown/markpact_blocks.py
pactown/network.py
pactown/orchestrator.py
pactown/parallel.py
pactown/platform.py
pactown/resolver.py
pactown/runner_api.py
pactown/sandbox_manager.py
pactown/security.py
pactown/service_runner.py
pactown/user_isolation.py
pactown/deploy/__init__.py
pactown/deploy/base.py
pactown/deploy/compose.py
pactown/deploy/docker.py
pactown/deploy/kubernetes.py
pactown/deploy/podman.py
pactown/deploy/quadlet.py
pactown/deploy/quadlet_api.py
pactown/deploy/quadlet_shell.py
pactown/registry/__init__.py
pactown/registry/client.py
pactown/registry/models.py
pactown/registry/server.py
pactown-0.1.100.dist-info/METADATA
pactown-0.1.100.dist-info/WHEEL
pactown-0.1.100.dist-info/entry_points.txt
pactown-0.1.100.dist-info/licenses/LICENSE
pactown-0.1.100.dist-info/RECORD
