Metadata-Version: 2.4
Name: pactown
Version: 0.1.100
Summary: Decentralized Service Ecosystem Orchestrator - Build interconnected microservices from Markdown using markpact
Project-URL: Homepage, https://github.com/wronai/pactown
Project-URL: Repository, https://github.com/wronai/pactown
Project-URL: Issues, https://github.com/wronai/pactown/issues
Author: wronai
License-Expression: Apache-2.0
License-File: LICENSE
Keywords: decentralized,ecosystem,markdown,markpact,microservices,orchestrator,sandbox
Classifier: Development Status :: 3 - Alpha
Classifier: Environment :: Console
Classifier: Intended Audience :: Developers
Classifier: License :: OSI Approved :: Apache Software License
Classifier: Programming Language :: Python :: 3
Classifier: Programming Language :: Python :: 3.10
Classifier: Programming Language :: Python :: 3.11
Classifier: Programming Language :: Python :: 3.12
Classifier: Programming Language :: Python :: 3.13
Classifier: Topic :: Software Development :: Build Tools
Classifier: Topic :: System :: Distributed Computing
Requires-Python: >=3.10
Requires-Dist: click>=8.0
Requires-Dist: fastapi>=0.100.0
Requires-Dist: httpx>=0.24.0
Requires-Dist: markpact>=0.1.10
Requires-Dist: pydantic>=2.0
Requires-Dist: pyyaml>=6.0
Requires-Dist: rich>=13.0
Requires-Dist: uvicorn>=0.20.0
Requires-Dist: watchfiles>=0.20.0
Provides-Extra: all
Requires-Dist: lolm>=0.1.6; extra == 'all'
Provides-Extra: dev
Requires-Dist: build; extra == 'dev'
Requires-Dist: bump2version>=1.0; extra == 'dev'
Requires-Dist: pytest-asyncio==0.23.4; extra == 'dev'
Requires-Dist: pytest-cov>=4.0; extra == 'dev'
Requires-Dist: pytest>=7.0; extra == 'dev'
Requires-Dist: ruff>=0.1; extra == 'dev'
Requires-Dist: twine; extra == 'dev'
Provides-Extra: llm
Requires-Dist: lolm>=0.1.6; extra == 'llm'
Provides-Extra: security
Requires-Dist: bandit>=1.7; extra == 'security'
Requires-Dist: pip-audit>=2.6; extra == 'security'
Requires-Dist: safety>=2.3; extra == 'security'
Requires-Dist: semgrep>=1.50; extra == 'security'
